lazo_index_service/__init__.py
lazo_index_service/client.py
lazo_index_service/errors.py
lazo_index_service/lazo_index_pb2.py
lazo_index_service/lazo_index_pb2_grpc.py
lazo_index_service-0.8.0.dist-info/METADATA
lazo_index_service-0.8.0.dist-info/WHEEL
lazo_index_service-0.8.0.dist-info/licenses/LICENSE.txt
lazo_index_service-0.8.0.dist-info/licenses/NOTICE.txt
lazo_index_service-0.8.0.dist-info/RECORD
