Metadata-Version: 2.4
Name: lazo-index-service
Version: 0.8.0
Summary: A Python client library for accessing the Lazo gRPC service
License: Apache-2.0
License-File: LICENSE.txt
License-File: NOTICE.txt
Keywords: auctus,datamart,lazo
Author: Fernando Chirigati
Author-email: fchirigati@nyu.edu
Maintainer: Remi Rampin
Maintainer-email: remi.rampin@nyu.edu
Requires-Python: >=3.9,<4.0
Classifier: Development Status :: 4 - Beta
Classifier: Intended Audience :: Science/Research
Classifier: License :: OSI Approved :: Apache Software License
Classifier: Operating System :: OS Independent
Classifier: Programming Language :: Python :: 3
Classifier: Programming Language :: Python :: 3.9
Classifier: Programming Language :: Python :: 3.10
Classifier: Programming Language :: Python :: 3.11
Classifier: Programming Language :: Python :: 3.12
Classifier: Programming Language :: Python :: 3.13
Classifier: Programming Language :: Python :: 3.14
Classifier: Programming Language :: Python :: 3 :: Only
Classifier: Topic :: Database :: Front-Ends
Classifier: Topic :: Scientific/Engineering :: Information Analysis
Requires-Dist: grpcio (>=1.42,<2)
Requires-Dist: protobuf (>=3.19)
Project-URL: Bug Tracker, https://gitlab.com/ViDA-NYU/auctus/auctus/-/issues
Project-URL: Homepage, https://gitlab.com/ViDA-NYU/auctus/lazo-index-service
Project-URL: Repository, https://gitlab.com/ViDA-NYU/auctus/lazo-index-service
